chatgpt_klient/__init__.py
chatgpt_klient/client.py
chatgpt_klient/consts.py
chatgpt_klient/exceptions.py
chatgpt_klient-0.8.0.dist-info/METADATA
chatgpt_klient-0.8.0.dist-info/WHEEL
chatgpt_klient-0.8.0.dist-info/top_level.txt
chatgpt_klient-0.8.0.dist-info/RECORD
